custom_dot_plot/__init__.py
custom_dot_plot/data.py
custom_dot_plot/example.py
custom_dot_plot/frontend/build/asset-manifest.json
custom_dot_plot/frontend/build/bootstrap.min.css
custom_dot_plot/frontend/build/bootstrap.min.css.map
custom_dot_plot/frontend/build/index.html
custom_dot_plot/frontend/build/static/css/main.8ccff0f8.css
custom_dot_plot/frontend/build/static/css/main.8ccff0f8.css.map
custom_dot_plot/frontend/build/static/js/main.42d71871.js
custom_dot_plot/frontend/build/static/js/main.42d71871.js.LICENSE.txt
custom_dot_plot/frontend/build/static/js/main.42d71871.js.map
custom_dot_plot-0.0.9.dist-info/LICENSE
custom_dot_plot-0.0.9.dist-info/METADATA
custom_dot_plot-0.0.9.dist-info/WHEEL
custom_dot_plot-0.0.9.dist-info/top_level.txt
custom_dot_plot-0.0.9.dist-info/RECORD
